{"name":"Excickkew","asigurat":"Neasigurat","varsta":"","datanasterii":"","phone":"86141881654","sex":"1","Adresa":null,"Localitate":"Sigulda","Judet":"","Talie":"","Greutate":"","Circumferinta_abdominala":"","Circumferinta_soldurilor":"","Tensiunea_arteriala_ortostatism":"","Tensiunea_arteriala_clinostatism":"","acuze":"<a href=https:\/\/vskamagrav.com\/>online kamagra mumbai","Antecedente_heredo_colaterale":"<a href=https:\/\/vskamagrav.com\/>online kamagra mumbai","antecedente_fiziologice":null,"Antecedente_personale_fiziologice":"<a href=https:\/\/vskamagrav.com\/>online kamagra mumbai","numar_nasteri":"","numar_sarcini":"","numar_avorturi":"","antecedente_patologice":["HTA"],"tip_dz":"Excickkew","grad_hta":"","antecedente_personale_patologice":null,"medicatia_curenta":"<a href=https:\/\/vskamagrav.com\/>online kamagra mumbai","loc_munca":"Non_Toxic","fumator":"Da_trecut","alcool":"Nu","pachete_an":"","an_nefumator":"","mese_zi":null,"legume":null,"fructe":null,"lactate":null,"fainoase":null,"proteine":null,"ml_alcool":"","alcool_zi":"","suplimente":null,"tegumente_mucoase_fanere":["normale"],"observatii_tegumente":"<a href=https:\/\/vskamagrav.com\/>online kamagra mumbai","tesut_conjuctiv_adipos":["normal_reprezentat"],"observatii_tesut":"<a href=https:\/\/vskamagrav.com\/>online kamagra mumbai","sistem_ganglionar":["NORMALE"],"observatii_ganglionar":"<a href=https:\/\/vskamagrav.com\/>online kamagra mumbai","muscular_osteo_articular":["normal"],"observatii_muscular":"<a href=https:\/\/vskamagrav.com\/>online kamagra mumbai","aparat_respirator":["normal"],"observatii_aparat_respirator":"<a href=https:\/\/vskamagrav.com\/>online kamagra mumbai","aparat_cardiovascular":["normal"],"observatii_cardiovascular":"<a href=https:\/\/vskamagrav.com\/>online kamagra mumbai","abdomen":["normal"],"observatii_abdomen":"<a href=https:\/\/vskamagrav.com\/>online kamagra mumbai","ficat_bila_splina":["normal"],"observatii_ficat":"<a href=https:\/\/vskamagrav.com\/>online kamagra mumbai","aparat_genito_urinar":["normal"],"observatii_genito_urinar":"<a href=https:\/\/vskamagrav.com\/>online kamagra mumbai","sistem_nervos":["normal"],"observatii_sistem_nervos":"<a href=https:\/\/vskamagrav.com\/>online kamagra mumbai","organe_de_simt":["normal"],"observatii_organe_de_simt":"<a href=https:\/\/vskamagrav.com\/>online kamagra mumbai","tiroida":["tiroida_palpabila"],"observatii_tiroida":"<a href=https:\/\/vskamagrav.com\/>online kamagra mumbai","consultari_suplimentare":["consult_medicina_interna"],"alte_consulturi":"<a href=https:\/\/vskamagrav.com\/>online kamagra mumbai","diagnostice":null,"recomandari":"<a href=https:\/\/vskamagrav.com\/>online kamagra mumbai","doctor":"","status":"","diagnostice_vechi":["status_supraponderal"],"diagnostice_noi":["status_supraponderal"],"observatii_diagnostice_noi":"<a href=https:\/\/vskamagrav.com\/>online kamagra mumbai","observatii_diagnostice_vechi":"<a href=https:\/\/vskamagrav.com\/>online kamagra mumbai","bilant_clinic":"urgenta_medicala"}